iotaescrow
