Metadata-Version: 2.1
Name: iotaescrow
Version: 0.0.2.3
Summary: Basic escrow utility using IOTA
Home-page: https://github.com/Tsangares/iotaescrow
Author-email: william.wyatt@cgu.edu
License: UNKNOWN
Platform: UNKNOWN
Classifier: Programming Language :: Python :: 3
Classifier: License :: OSI Approved :: MIT License
Classifier: Operating System :: OS Independent
Requires-Python: >=3.7
